tlsleuth/TLSleuthAscii.txt
tlsleuth/__init__.py
tlsleuth/__main__.py
tlsleuth/cli.py
tlsleuth/logger_setup.py
tlsleuth/logging.conf
tlsleuth/output.py
tlsleuth/scanner.py
tlsleuth/utils.py
tlsleuth-0.1.0.dist-info/licenses/LICENSE
tlsleuth-0.1.0.dist-info/METADATA
tlsleuth-0.1.0.dist-info/WHEEL
tlsleuth-0.1.0.dist-info/entry_points.txt
tlsleuth-0.1.0.dist-info/top_level.txt
tlsleuth-0.1.0.dist-info/RECORD
