Metadata-Version: 2.4
Name: tlsleuth
Version: 0.1.0
Summary: Scan hosts for weak TLS/SSL settings and certificate issues.
Author-email: Rafael Fron <range.bay8483@eagereverest.com>
Maintainer-email: Rafael Fron <range.bay8483@eagereverest.com>
License: MIT
Project-URL: Repository, https://github.com/RafaLe0/TLSleuth
Project-URL: Issues, https://github.com/RafaLe0/TLSleuth/issues
Keywords: tls,ssl,certificates,https,encryption,security
Classifier: Development Status :: 3 - Alpha
Classifier: Intended Audience :: System Administrators
Classifier: Intended Audience :: Information Technology
Classifier: Topic :: Security
Classifier: Topic :: Internet :: WWW/HTTP
Classifier: License :: OSI Approved :: MIT License
Classifier: Programming Language :: Python :: 3
Classifier: Programming Language :: Python :: 3.9
Classifier: Programming Language :: Python :: 3.10
Classifier: Programming Language :: Python :: 3.11
Classifier: Programming Language :: Python :: 3.12
Classifier: Operating System :: OS Independent
Requires-Python: >=3.9
License-File: LICENSE
Provides-Extra: test
Requires-Dist: pytest>=7.0; extra == "test"
Dynamic: license-file
